{
  "_industry": "clinic",
  "_displayName": "عيادة / مستشفى / مجمع طبي",
  "_description": "أتمتات جاهزة للقطاع الصحي — حجز مواعيد، تذكيرات، متابعة المرضى",
  "_version": "5.0",
  "scenarios": [
    {
      "id": "clinic-01",
      "name": "تأكيد الموعد تلقائياً",
      "nameEn": "Auto Appointment Confirmation",
      "description": "لما مريض يحجز موعد → يوصله تأكيد واتساب + إيميل",
      "trigger": { "tool": "webhook", "event": "new_booking" },
      "actions": [
        { "tool": "whatsapp", "action": "send_message", "desc": "رسالة تأكيد فيها التاريخ والوقت والطبيب" },
        { "tool": "gmail", "action": "send_email", "desc": "إيميل تأكيد رسمي" },
        { "tool": "google-sheets", "action": "insert_row", "desc": "تسجيل الحجز في جدول المواعيد" }
      ],
      "timeSaved": "5 دقائق لكل موعد",
      "priority": "عالي"
    },
    {
      "id": "clinic-02",
      "name": "تذكير قبل الموعد بـ 24 ساعة",
      "nameEn": "24h Appointment Reminder",
      "description": "كل يوم الساعة 8 صباح → يرسل تذكير لمواعيد بكرة",
      "trigger": { "tool": "schedule", "event": "cron_expression", "config": "0 8 * * *" },
      "actions": [
        { "tool": "google-sheets", "action": "read_rows", "desc": "يجيب مواعيد بكرة من الجدول" },
        { "tool": "ai", "action": "askAi", "desc": "يصيغ رسالة تذكير شخصية لكل مريض" },
        { "tool": "whatsapp", "action": "send_message", "desc": "يرسل التذكير عبر واتساب" }
      ],
      "timeSaved": "30 دقيقة يومياً",
      "priority": "عالي"
    },
    {
      "id": "clinic-03",
      "name": "متابعة بعد الزيارة",
      "nameEn": "Post-Visit Follow-up",
      "description": "بعد 3 أيام من الزيارة → رسالة اطمئنان + استبيان رضا",
      "trigger": { "tool": "schedule", "event": "cron_expression", "config": "0 10 * * *" },
      "actions": [
        { "tool": "google-sheets", "action": "read_rows", "desc": "يجيب زيارات قبل 3 أيام" },
        { "tool": "whatsapp", "action": "send_message", "desc": "رسالة اطمئنان" },
        { "tool": "gmail", "action": "send_email", "desc": "رابط استبيان رضا" }
      ],
      "timeSaved": "15 دقيقة يومياً",
      "priority": "متوسط"
    },
    {
      "id": "clinic-04",
      "name": "تسجيل مريض جديد",
      "nameEn": "New Patient Registration",
      "description": "لما مريض جديد يسجل → يتسجل في النظام + يوصله ترحيب",
      "trigger": { "tool": "webhook", "event": "new_patient" },
      "actions": [
        { "tool": "google-sheets", "action": "insert_row", "desc": "إضافة في سجل المرضى" },
        { "tool": "hubspot", "action": "create_contact", "desc": "إنشاء جهة اتصال في CRM" },
        { "tool": "whatsapp", "action": "send_message", "desc": "رسالة ترحيب + معلومات العيادة" },
        { "tool": "gmail", "action": "send_email", "desc": "إيميل ترحيب + نماذج مطلوبة" }
      ],
      "timeSaved": "10 دقائق لكل مريض جديد",
      "priority": "عالي"
    },
    {
      "id": "clinic-05",
      "name": "تقرير يومي للمدير",
      "nameEn": "Daily Director Report",
      "description": "كل مساء → تقرير بعدد المواعيد والإيرادات والإلغاءات",
      "trigger": { "tool": "schedule", "event": "cron_expression", "config": "0 18 * * *" },
      "actions": [
        { "tool": "google-sheets", "action": "read_rows", "desc": "جمع بيانات اليوم" },
        { "tool": "ai", "action": "askAi", "desc": "تحليل وتلخيص" },
        { "tool": "whatsapp", "action": "send_message", "desc": "إرسال التقرير للمدير" }
      ],
      "timeSaved": "20 دقيقة يومياً",
      "priority": "متوسط"
    },
    {
      "id": "clinic-06",
      "name": "تذكير بالمراجعة الدورية",
      "nameEn": "Periodic Checkup Reminder",
      "description": "كل أسبوع → يفحص المرضى اللي حان وقت مراجعتهم ويرسل لهم",
      "trigger": { "tool": "schedule", "event": "cron_expression", "config": "0 9 * * 1" },
      "actions": [
        { "tool": "google-sheets", "action": "read_rows", "desc": "مرضى حان وقت مراجعتهم" },
        { "tool": "whatsapp", "action": "send_message", "desc": "تذكير بالمراجعة + رابط حجز" }
      ],
      "timeSaved": "45 دقيقة أسبوعياً",
      "priority": "متوسط"
    }
  ]
}
