{"_autoflow":{"version":"5.0","toolId":"microsoft-teams","toolNameAr":"مايكروسوفت تيمز"},"piece":{"packageType":"REGISTRY","pieceType":"OFFICIAL","pieceName":"@activepieces/piece-microsoft-teams","pieceVersion":"~0.2.1"},"auth":{"type":"OAUTH2"},"triggers":{"new_message":{"displayName":"New Message in Channel","type":"POLLING","props":{"teamId":{"type":"DROPDOWN","required":true},"channelId":{"type":"DROPDOWN","required":true}},"_copyPaste":{"type":"PIECE_TRIGGER","settings":{"pieceName":"@activepieces/piece-microsoft-teams","pieceVersion":"~0.2.1","pieceType":"OFFICIAL","packageType":"REGISTRY","triggerName":"new_message","input":{"teamId":"","channelId":""},"inputUiInfo":{}},"valid":false,"name":"trigger"}}},"actions":{"send_channel_message":{"displayName":"Send Channel Message","props":{"teamId":{"type":"DROPDOWN","required":true},"channelId":{"type":"DROPDOWN","required":true},"content":{"type":"LONG_TEXT","required":true}},"_copyPaste":{"type":"PIECE","settings":{"pieceName":"@activepieces/piece-microsoft-teams","pieceVersion":"~0.2.1","pieceType":"OFFICIAL","packageType":"REGISTRY","actionName":"send_channel_message","input":{"teamId":"","channelId":"","content":""},"inputUiInfo":{}},"valid":false,"name":"step_N"}},"send_chat_message":{"displayName":"Send Chat Message","props":{"chatId":{"type":"SHORT_TEXT","required":true},"content":{"type":"LONG_TEXT","required":true}},"_copyPaste":{"type":"PIECE","settings":{"pieceName":"@activepieces/piece-microsoft-teams","pieceVersion":"~0.2.1","pieceType":"OFFICIAL","packageType":"REGISTRY","actionName":"send_chat_message","input":{"chatId":"","content":""},"inputUiInfo":{}},"valid":false,"name":"step_N"}}}}
